memoripy/__init__.py
memoripy/implemented_models.py
memoripy/in_memory_storage.py
memoripy/json_storage.py
memoripy/main.py
memoripy/memory_manager.py
memoripy/memory_store.py
memoripy/model.py
memoripy/storage.py
memoripy-0.1.2.dist-info/LICENSE
memoripy-0.1.2.dist-info/METADATA
memoripy-0.1.2.dist-info/WHEEL
memoripy-0.1.2.dist-info/top_level.txt
memoripy-0.1.2.dist-info/RECORD
