Metadata-Version: 2.1
Name: memoripy
Version: 0.1.2
Summary: Memoripy provides context-aware memory management with support for OpenAI and Ollama APIs, offering structured short-term and long-term memory storage for interactive applications.
Home-page: https://github.com/caspianmoon/memoripy
Author: Khazar Ayaz
Author-email: khazar.ayaz@personnoai.com
Classifier: Programming Language :: Python :: 3
Classifier: License :: OSI Approved :: MIT License
Classifier: Operating System :: OS Independent
Requires-Python: >=3.8
License-File: LICENSE
Requires-Dist: aiohappyeyeballs==2.4.3
Requires-Dist: aiohttp==3.10.10
Requires-Dist: aiosignal==1.3.1
Requires-Dist: annotated-types==0.7.0
Requires-Dist: anyio==4.6.2.post1
Requires-Dist: attrs==24.2.0
Requires-Dist: certifi==2024.8.30
Requires-Dist: charset-normalizer==3.4.0
Requires-Dist: distro==1.9.0
Requires-Dist: faiss-cpu==1.8.0.post1
Requires-Dist: frozenlist==1.5.0
Requires-Dist: h11==0.14.0
Requires-Dist: httpcore==1.0.6
Requires-Dist: httpx==0.27.2
Requires-Dist: idna==3.10
Requires-Dist: jiter==0.7.0
Requires-Dist: joblib==1.4.2
Requires-Dist: jsonpatch==1.33
Requires-Dist: jsonpointer==3.0.0
Requires-Dist: langchain==0.3.7
Requires-Dist: langchain-core==0.3.15
Requires-Dist: langchain-ollama==0.2.0
Requires-Dist: langchain-openai==0.2.5
Requires-Dist: langchain-text-splitters==0.3.2
Requires-Dist: langsmith==0.1.139
Requires-Dist: multidict==6.1.0
Requires-Dist: networkx==3.4.2
Requires-Dist: numpy==1.26.4
Requires-Dist: ollama==0.3.3
Requires-Dist: openai==1.53.0
Requires-Dist: orjson==3.10.11
Requires-Dist: packaging==24.1
Requires-Dist: propcache==0.2.0
Requires-Dist: pydantic==2.9.2
Requires-Dist: pydantic-core==2.23.4
Requires-Dist: PyYAML==6.0.2
Requires-Dist: regex==2024.9.11
Requires-Dist: requests==2.32.3
Requires-Dist: requests-toolbelt==1.0.0
Requires-Dist: scikit-learn==1.5.2
Requires-Dist: scipy==1.14.1
Requires-Dist: setuptools==75.3.0
Requires-Dist: sniffio==1.3.1
Requires-Dist: SQLAlchemy==2.0.36
Requires-Dist: tenacity==9.0.0
Requires-Dist: threadpoolctl==3.5.0
Requires-Dist: tiktoken==0.8.0
Requires-Dist: tqdm==4.66.6
Requires-Dist: typing-extensions==4.12.2
Requires-Dist: urllib3==2.2.3
Requires-Dist: yarl==1.17.1
